predacons_gui/__init__.py
predacons_gui/src/__init__.py
predacons_gui/src/predacons_gui.py
predacons_gui/src/webapp.py
predacons_gui-0.0.107.dist-info/LICENSE
predacons_gui-0.0.107.dist-info/METADATA
predacons_gui-0.0.107.dist-info/WHEEL
predacons_gui-0.0.107.dist-info/entry_points.txt
predacons_gui-0.0.107.dist-info/top_level.txt
predacons_gui-0.0.107.dist-info/RECORD
